MANIFEST.in
README.md
setup.py
syst3m/.version
syst3m/README.md
syst3m/__init__.py
syst3m/__main__.py
syst3m.egg-info/PKG-INFO
syst3m.egg-info/SOURCES.txt
syst3m.egg-info/dependency_links.txt
syst3m.egg-info/not-zip-safe
syst3m.egg-info/requires.txt
syst3m.egg-info/top_level.txt
syst3m/classes/__init__.py
syst3m/classes/browser/__init__.py
syst3m/classes/browser/drivers/linux/chromedriver
syst3m/classes/browser/drivers/linux/geckodriver
syst3m/classes/browser/drivers/macos/chromedriver
syst3m/classes/browser/drivers/macos/geckodriver
syst3m/classes/cache/__init__.py
syst3m/classes/cache/fork.py
syst3m/classes/config/__init__.py
syst3m/classes/console/__init__.py
syst3m/classes/disks/__init__.py
syst3m/classes/exceptions/__init__.py
syst3m/classes/keyboard/__init__.py
syst3m/classes/mouse/__init__.py
syst3m/classes/screen/__init__.py
syst3m/classes/service/__init__.py
syst3m/classes/system/__init__.py
syst3m/classes/utils/__init__.py
syst3m/static/media/folders/edits.paint
syst3m/static/media/folders/folder.png
syst3m/static/media/folders/python.png
syst3m/static/media/folders/vandenberghinc.png
syst3m/static/media/logos/python.png
syst3m/static/media/logos/vandenberghinc.png