Metadata-Version: 1.0
Name: syst3m
Version: 2.17.5
Summary: Some description.
Home-page: http://github.com/vandenberghinc/syst3m
Author: Daan van den Bergh
Author-email: vandenberghinc.contact@gmail.com
License: MIT
Platform: UNKNOWN
